{
  "schema_version": "1",
  "name": "Cofoundry Templates",
  "description": "Proxmox VM templates built with Cofoundry",
  "generated_at": "2026-07-21T03:51:33.047Z",
  "groups": [
    {
      "id": "almalinux",
      "display_name": "AlmaLinux",
      "description": null,
      "templates": [
        {
          "name": "almalinux-10-amd64",
          "display": "AlmaLinux 10",
          "arch": "amd64",
          "sha256": "d2b420a7a3c5ec33b2f14e790e652c7dce43412a0f8d39bcf808765272f4b935",
          "size": 1018212444,
          "url": "https://cofoundry.cdn.convoypanel.com/templates/almalinux/almalinux-10-amd64/d2b420a7a3c5ec33b2f14e790e652c7dce43412a0f8d39bcf808765272f4b935.vma.zst",
          "built_at": "2026-07-21T02:38:25Z",
          "suggested_vmid": 6002
        },
        {
          "name": "almalinux-8-amd64",
          "display": "AlmaLinux 8",
          "arch": "amd64",
          "sha256": "d775b6f13cc2b463cf975a9c256bfdf65c27ca525a93dcfa2c899d999e87dbda",
          "size": 1358716523,
          "url": "https://cofoundry.cdn.convoypanel.com/templates/almalinux/almalinux-8-amd64/d775b6f13cc2b463cf975a9c256bfdf65c27ca525a93dcfa2c899d999e87dbda.vma.zst",
          "built_at": "2026-07-21T02:38:54Z",
          "suggested_vmid": 6000
        },
        {
          "name": "almalinux-9-amd64",
          "display": "AlmaLinux 9",
          "arch": "amd64",
          "sha256": "8bfbbb51f35fd4ebb8b0c1fcdb452da7bb2d4fb1002db054d9d9bc3fab224cf2",
          "size": 1224207865,
          "url": "https://cofoundry.cdn.convoypanel.com/templates/almalinux/almalinux-9-amd64/8bfbbb51f35fd4ebb8b0c1fcdb452da7bb2d4fb1002db054d9d9bc3fab224cf2.vma.zst",
          "built_at": "2026-07-21T02:37:08Z",
          "suggested_vmid": 6001
        }
      ]
    },
    {
      "id": "debian",
      "display_name": "Debian",
      "description": null,
      "templates": [
        {
          "name": "debian-11-amd64",
          "display": "Debian 11 (Bullseye)",
          "arch": "amd64",
          "sha256": "b86364f9ccfc97d01eac421090a8a737687bc64368e02b278f8e67be9aedf09b",
          "size": 462844860,
          "url": "https://cofoundry.cdn.convoypanel.com/templates/debian/debian-11-amd64/b86364f9ccfc97d01eac421090a8a737687bc64368e02b278f8e67be9aedf09b.vma.zst",
          "built_at": "2026-07-21T02:35:32Z",
          "suggested_vmid": 4000
        },
        {
          "name": "debian-12-amd64",
          "display": "Debian 12 (Bookworm)",
          "arch": "amd64",
          "sha256": "0db507765e2ed0092bb771b1dba5dbb5f5ca01cfce4a1de922ae46da0e70f7dd",
          "size": 536534950,
          "url": "https://cofoundry.cdn.convoypanel.com/templates/debian/debian-12-amd64/0db507765e2ed0092bb771b1dba5dbb5f5ca01cfce4a1de922ae46da0e70f7dd.vma.zst",
          "built_at": "2026-07-21T02:49:49Z",
          "suggested_vmid": 4001
        },
        {
          "name": "debian-13-amd64",
          "display": "Debian 13 (Trixie)",
          "arch": "amd64",
          "sha256": "64e42c5b0fd597f48e8cab84171484a18dbbb47f3c5864af08b4791702fdfbc8",
          "size": 561911966,
          "url": "https://cofoundry.cdn.convoypanel.com/templates/debian/debian-13-amd64/64e42c5b0fd597f48e8cab84171484a18dbbb47f3c5864af08b4791702fdfbc8.vma.zst",
          "built_at": "2026-07-21T02:49:32Z",
          "suggested_vmid": 4002
        }
      ]
    },
    {
      "id": "rocky-linux",
      "display_name": "Rocky Linux",
      "description": null,
      "templates": [
        {
          "name": "rocky-linux-10-amd64",
          "display": "Rocky Linux 10",
          "arch": "amd64",
          "sha256": "1adfeed3fba7f7c7595fab8307d389f50e815b29fd88c9e79bac5e5925e08aac",
          "size": 1023318468,
          "url": "https://cofoundry.cdn.convoypanel.com/templates/rocky-linux/rocky-linux-10-amd64/1adfeed3fba7f7c7595fab8307d389f50e815b29fd88c9e79bac5e5925e08aac.vma.zst",
          "built_at": "2026-07-21T02:58:26Z",
          "suggested_vmid": 5002
        },
        {
          "name": "rocky-linux-8-amd64",
          "display": "Rocky Linux 8",
          "arch": "amd64",
          "sha256": "8a46741cb0de251226913fed401f1501a39850db91a365be1c7adb88a4d914cf",
          "size": 1354587102,
          "url": "https://cofoundry.cdn.convoypanel.com/templates/rocky-linux/rocky-linux-8-amd64/8a46741cb0de251226913fed401f1501a39850db91a365be1c7adb88a4d914cf.vma.zst",
          "built_at": "2026-07-21T02:56:33Z",
          "suggested_vmid": 5000
        },
        {
          "name": "rocky-linux-9-amd64",
          "display": "Rocky Linux 9",
          "arch": "amd64",
          "sha256": "9b96e7c5ae7f0668d53b2fddda3a5700632c1f8144f49254eedc3a4a4880bcc4",
          "size": 1232521793,
          "url": "https://cofoundry.cdn.convoypanel.com/templates/rocky-linux/rocky-linux-9-amd64/9b96e7c5ae7f0668d53b2fddda3a5700632c1f8144f49254eedc3a4a4880bcc4.vma.zst",
          "built_at": "2026-07-21T03:11:00Z",
          "suggested_vmid": 5001
        }
      ]
    },
    {
      "id": "ubuntu",
      "display_name": "Ubuntu",
      "description": null,
      "templates": [
        {
          "name": "ubuntu-22.04-amd64",
          "display": "Ubuntu 22.04 LTS (Jammy Jellyfish)",
          "arch": "amd64",
          "sha256": "04df667c9c9e1277147353d86caf23528389c6ca11c73828abf0a67e01e44245",
          "size": 1326886768,
          "url": "https://cofoundry.cdn.convoypanel.com/templates/ubuntu/ubuntu-22.04-amd64/04df667c9c9e1277147353d86caf23528389c6ca11c73828abf0a67e01e44245.vma.zst",
          "built_at": "2026-07-21T03:13:59Z",
          "suggested_vmid": 1002
        },
        {
          "name": "ubuntu-24.04-amd64",
          "display": "Ubuntu 24.04 LTS (Noble Numbat)",
          "arch": "amd64",
          "sha256": "1fc6bfc31c158d18358c171c07898a88d5ecbca6bc5572c2b4149b78cbb41e51",
          "size": 1425320017,
          "url": "https://cofoundry.cdn.convoypanel.com/templates/ubuntu/ubuntu-24.04-amd64/1fc6bfc31c158d18358c171c07898a88d5ecbca6bc5572c2b4149b78cbb41e51.vma.zst",
          "built_at": "2026-07-21T03:19:00Z",
          "suggested_vmid": 1003
        },
        {
          "name": "ubuntu-25.10-amd64",
          "display": "Ubuntu 25.10 (Questing Quokka)",
          "arch": "amd64",
          "sha256": "589e0f24aedb5ae4af59719cf848b251371d8b8b3d6c6a69646272704cc87b98",
          "size": 1541795738,
          "url": "https://cofoundry.cdn.convoypanel.com/templates/ubuntu/ubuntu-25.10-amd64/589e0f24aedb5ae4af59719cf848b251371d8b8b3d6c6a69646272704cc87b98.vma.zst",
          "built_at": "2026-07-21T03:19:57Z",
          "suggested_vmid": 1004
        },
        {
          "name": "ubuntu-26.04-amd64",
          "display": "Ubuntu 26.04 LTS (Resolute Raccoon)",
          "arch": "amd64",
          "sha256": "2fe4b9ecafb73c251bfcbbb1db2ccf9e0dc39358d0a5ec3c6787f87cb4bd568b",
          "size": 1560431944,
          "url": "https://cofoundry.cdn.convoypanel.com/templates/ubuntu/ubuntu-26.04-amd64/2fe4b9ecafb73c251bfcbbb1db2ccf9e0dc39358d0a5ec3c6787f87cb4bd568b.vma.zst",
          "built_at": "2026-07-21T03:36:39Z",
          "suggested_vmid": 1005
        }
      ]
    }
  ]
}
